LICENSE
README.md
setup.py
PyBj.egg-info/PKG-INFO
PyBj.egg-info/SOURCES.txt
PyBj.egg-info/dependency_links.txt
PyBj.egg-info/top_level.txt
pybj/__init__.py
pybj/__main__.py
pybj/pybj_class.py
pybj/pybj_gameplay.py