Metadata-Version: 2.1
Name: PyBj
Version: 1.0.220405.1
Summary: PyBj (Python Blackjack)
Home-page: https://github.com/destrianto/pybj
Download-URL: https://github.com/destrianto/pybj/releases/download/1.0.220405.0001/pybj_1.0.220405.0001.zip
Author: Ade Destrianto
Author-email: ade.destrianto@mail.ru
License: MIT
Keywords: blackjack,games
Platform: UNKNOWN
Classifier: Environment :: Console
Classifier: Intended Audience :: End Users/Desktop
Classifier: License :: OSI Approved :: MIT License
Classifier: Natural Language :: English
Classifier: Programming Language :: Python :: 3.9
Classifier: Topic :: Games/Entertainment
Requires-Python: >=3.9
License-File: LICENSE
